{
  "className": "org.ccguyka.NestedCoffeeMachineTest",
  "name": "Nested Coffee Machine",
  "scenarios": [
    {
      "className": "org.ccguyka.NestedCoffeeMachineTest",
      "testMethodName": "brew_coffee",
      "description": "brew coffee",
      "tagIds": [],
      "explicitParameters": [],
      "derivedParameters": [],
      "casesAsTable": false,
      "scenarioCases": [
        {
          "caseNr": 1,
          "steps": [
            {
              "name": "have a coffee machine",
              "words": [
                {
                  "value": "Given",
                  "isIntroWord": true
                },
                {
                  "value": "have a coffee machine"
                }
              ],
              "status": "PASSED",
              "durationInNanos": 104134
            },
            {
              "name": "add coffee beans",
              "words": [
                {
                  "value": "and",
                  "isIntroWord": true
                },
                {
                  "value": "add coffee beans"
                },
                {
                  "value": "Nicaragua",
                  "argumentInfo": {
                    "argumentName": "beans",
                    "formattedValue": "Nicaragua"
                  }
                }
              ],
              "status": "PASSED",
              "durationInNanos": 64045
            },
            {
              "name": "add hot water",
              "words": [
                {
                  "value": "and",
                  "isIntroWord": true
                },
                {
                  "value": "add hot water"
                }
              ],
              "status": "PASSED",
              "durationInNanos": 112445
            },
            {
              "name": "i brew coffee",
              "words": [
                {
                  "value": "When",
                  "isIntroWord": true
                },
                {
                  "value": "i brew coffee"
                }
              ],
              "status": "PASSED",
              "durationInNanos": 111956
            },
            {
              "name": "the coffee tastes good",
              "words": [
                {
                  "value": "Then",
                  "isIntroWord": true
                },
                {
                  "value": "the coffee tastes good"
                }
              ],
              "status": "PASSED",
              "durationInNanos": 133955
            }
          ],
          "explicitArguments": [],
          "derivedArguments": [],
          "success": true,
          "durationInNanos": 18044891
        }
      ],
      "durationInNanos": 18044891,
      "executionStatus": "SUCCESS"
    },
    {
      "className": "org.ccguyka.NestedCoffeeMachineTest",
      "testMethodName": "brew_coffee_without_beans",
      "description": "brew coffee without beans",
      "tagIds": [],
      "explicitParameters": [],
      "derivedParameters": [],
      "casesAsTable": false,
      "scenarioCases": [
        {
          "caseNr": 1,
          "steps": [
            {
              "name": "have a coffee machine",
              "words": [
                {
                  "value": "Given",
                  "isIntroWord": true
                },
                {
                  "value": "have a coffee machine"
                }
              ],
              "status": "PASSED",
              "durationInNanos": 34222
            },
            {
              "name": "add hot water",
              "words": [
                {
                  "value": "and",
                  "isIntroWord": true
                },
                {
                  "value": "add hot water"
                }
              ],
              "status": "PASSED",
              "durationInNanos": 43022
            },
            {
              "name": "i brew coffee",
              "words": [
                {
                  "value": "When",
                  "isIntroWord": true
                },
                {
                  "value": "i brew coffee"
                }
              ],
              "status": "PASSED",
              "durationInNanos": 66489
            },
            {
              "name": "some ingrediant is missing",
              "words": [
                {
                  "value": "Then",
                  "isIntroWord": true
                },
                {
                  "value": "some ingrediant is missing"
                },
                {
                  "value": "Beans",
                  "argumentInfo": {
                    "argumentName": "ingrediant",
                    "formattedValue": "Beans"
                  }
                }
              ],
              "status": "PASSED",
              "durationInNanos": 411156
            }
          ],
          "explicitArguments": [],
          "derivedArguments": [],
          "success": true,
          "durationInNanos": 946978
        }
      ],
      "durationInNanos": 946978,
      "executionStatus": "SUCCESS"
    },
    {
      "className": "org.ccguyka.NestedCoffeeMachineTest",
      "testMethodName": "brew_coffee_without_water",
      "description": "brew coffee without water",
      "tagIds": [],
      "explicitParameters": [],
      "derivedParameters": [],
      "casesAsTable": false,
      "scenarioCases": [
        {
          "caseNr": 1,
          "steps": [
            {
              "name": "have a coffee machine",
              "words": [
                {
                  "value": "Given",
                  "isIntroWord": true
                },
                {
                  "value": "have a coffee machine"
                }
              ],
              "status": "PASSED",
              "durationInNanos": 34222
            },
            {
              "name": "add coffee beans",
              "words": [
                {
                  "value": "and",
                  "isIntroWord": true
                },
                {
                  "value": "add coffee beans"
                },
                {
                  "value": "Nicaragua",
                  "argumentInfo": {
                    "argumentName": "beans",
                    "formattedValue": "Nicaragua"
                  }
                }
              ],
              "status": "PASSED",
              "durationInNanos": 288444
            },
            {
              "name": "i brew coffee",
              "words": [
                {
                  "value": "When",
                  "isIntroWord": true
                },
                {
                  "value": "i brew coffee"
                }
              ],
              "status": "PASSED",
              "durationInNanos": 56222
            },
            {
              "name": "some ingrediant is missing",
              "words": [
                {
                  "value": "Then",
                  "isIntroWord": true
                },
                {
                  "value": "some ingrediant is missing"
                },
                {
                  "value": "Water",
                  "argumentInfo": {
                    "argumentName": "ingrediant",
                    "formattedValue": "Water"
                  }
                }
              ],
              "status": "PASSED",
              "durationInNanos": 252267
            }
          ],
          "explicitArguments": [],
          "derivedArguments": [],
          "success": true,
          "durationInNanos": 1003689
        }
      ],
      "durationInNanos": 1003689,
      "executionStatus": "SUCCESS"
    }
  ],
  "tagMap": {}
}